odoo/addons/website_hide_portal_my_timesheets/README.rst
odoo/addons/website_hide_portal_my_timesheets/__init__.py
odoo/addons/website_hide_portal_my_timesheets/__manifest__.py
odoo/addons/website_hide_portal_my_timesheets/controllers/__init__.py
odoo/addons/website_hide_portal_my_timesheets/controllers/portal.py
odoo/addons/website_hide_portal_my_timesheets/readme/CONFIGURE.rst
odoo/addons/website_hide_portal_my_timesheets/readme/CONTRIBUTORS.rst
odoo/addons/website_hide_portal_my_timesheets/readme/DESCRIPTION.rst
odoo/addons/website_hide_portal_my_timesheets/static/description/icon.png
odoo/addons/website_hide_portal_my_timesheets/static/description/index.html
odoo/addons/website_hide_portal_my_timesheets/views/hr_timesheet_portal_template.xml
odoo_addon_website_hide_portal_my_timesheets-16.0.1.0.0.1.dist-info/METADATA
odoo_addon_website_hide_portal_my_timesheets-16.0.1.0.0.1.dist-info/WHEEL
odoo_addon_website_hide_portal_my_timesheets-16.0.1.0.0.1.dist-info/top_level.txt
odoo_addon_website_hide_portal_my_timesheets-16.0.1.0.0.1.dist-info/RECORD
